{
  "site": {
    "name": "Michael Yuan",
    "shortName": "Michael Yuan",
    "tagline": "Photography",
    "instagramUrl": "https://instagram.com/ilikecalculus",
    "blogUrl": "https://ilikecalculus.substack.com/"
  },
  "about": {
    "title": "About",
    "paragraphs": [
      "Hey there! I’m Michael Yuan.",
      "I split my time between building software and making art. By day, I’m a software engineer at Figma, working on tools that help teams design and build together."
    ],
    "image": {
      "src": "/media/about/about-20240831-dscf6193.jpg",
      "width": 4365,
      "height": 5456,
      "alt": "About portrait"
    }
  },
  "contact": {
    "title": "Contact",
    "paragraphs": [
      "I’m a visual artist working in the medium of photography, motivated by reframing the familiar. I’m drawn to the overlooked surfaces and objects of the world we build—and the marks they accumulate. Through perspective play, I shrink, flatten, and contort the everyday to draw out the subtle presence of humanity as residue: wear, repair, intention, neglect. I search for quiet solitude—and for the memories of places, things, and people that have become more invisible as time and culture shift.",
      "Looking to collaborate, share an idea, or ask a question? Send me a message—I’d love to hear from you. If you’re curious, I’ll also tell you the origin story behind ilikecalculus."
    ],
    "image": {
      "src": "/media/contact/banner.jpg",
      "width": 2500,
      "height": 833,
      "alt": "Contact portrait"
    }
  },
  "press": [
    {
      "outlet": "Leica Blog",
      "title": "Michael Yuan: The Bridge",
      "url": "https://lfi-online.de/ceemes/en/blog/michael-yuan-the-bridge-2693.html"
    },
    {
      "outlet": "SFGate",
      "title": "See the Golden Gate Bridge like you never have before",
      "url": "https://www.sfgate.com/living/article/Golden-Gate-Bridge-photographer-Michael-Yuan-15668793.php"
    },
    {
      "outlet": "PetaPixel",
      "title": "The Bridge, Reconstructed: A Different Perspective of the Golden Gate Bridge",
      "url": "https://petapixel.com/2020/10/05/the-bridge-reconstructed-a-different-perspective-of-the-golden-gate-bridge/"
    },
    {
      "outlet": "LifeFramer",
      "title": "Reimagining an Icon",
      "url": "https://www.life-framer.com/michael-yuan/"
    },
    {
      "outlet": "Artwort",
      "title": "The Bridge, Reconstructed – Il Golden Gate Bridge da ricostruire nelle fotografie di Michael Yuan",
      "url": "https://www.artwort.com/2020/11/03/fotografia/the-bridge-reconstructed-michael-yuan/"
    },
    {
      "outlet": "Plain Magazine",
      "title": "The Golden Gate Bridge, Deconstructed and Delightfully Unrecognizable",
      "url": "https://plainmagazine.com/michael-yuan-golden-gate-bridge/"
    },
    {
      "outlet": "Architectural Photography Almanac",
      "title": "Math Aficionado Michael Yuan Hones in on the Golden Ratios of the Golden Gate Bridge",
      "url": "https://apalmanac.com/potw/math-aficionado-michael-yuan-hones-in-on-the-golden-ratios-of-the-golden-gate-bridge-13773"
    },
    {
      "outlet": "Dodho Magazine",
      "title": "Golden Gate; The Bridge, Reconstructed by Michael Yuan",
      "url": "https://www.dodho.com/golden-gate-the-bridge-reconstructed-by-michael-yuan/"
    },
    {
      "outlet": "The Photo Argus",
      "title": "Incredible Pictures of Basketball Courts – “Urban Courts” by Michael Yuan",
      "url": "https://www.thephotoargus.com/incredible-pictures-of-basketball-courts-urban-courts-by-michael-yuan/"
    },
    {
      "outlet": "Le Blog de Fabien Ribery",
      "title": "The Bridge, l’âme du métal, par Michael Yuan, ingénieur photographe",
      "url": "https://lintervalle.blog/2022/08/03/the-bridge-lame-du-metal-par-michael-yuan-ingenieur-photographe/"
    },
    {
      "outlet": "Glasstire",
      "title": "A Shockingly Modernist Project and Others: Four Books of Photographs",
      "url": "https://glasstire.com/2023/01/04/a-shockingly-modernist-project-and-others-four-books-of-photographs/"
    }
  ],
  "where": {
    "locations": [
      {
        "id": "dc8310fa-5d26-4ec7-8380-4cb104de57db",
        "label": "New York City",
        "latitude": 40.718117449032434,
        "longitude": -73.95747908497457,
        "at": "2026-01-02T17:00:00.000Z",
        "note": "Finally in NYC after a month of traveling"
      },
      {
        "id": "ecf5e8ba-d4da-4705-b6d5-5fffb50b8f22",
        "label": "Hong Kong",
        "latitude": 22.28117547134755,
        "longitude": 114.18595157291284,
        "at": "2026-02-28T00:45:00.000Z",
        "note": "Starting my sabbatical in Hong Kong"
      },
      {
        "id": "43dce09f-7884-4629-9dec-c4db9fb26251",
        "label": "Taipei",
        "latitude": 25.03346844531645,
        "longitude": 121.56495420459811,
        "at": "2025-12-30T13:50:00.000Z",
        "note": "NYE countdown in Taipei with DQ"
      },
      {
        "id": "3562c808-96dd-4ebf-96ea-b76e7a5cf38c",
        "label": "Kanazawa",
        "latitude": 36.57864660027996,
        "longitude": 136.64766678471085,
        "at": "2026-03-04T11:30:00.000Z",
        "note": "Flew into Tokyo and trained straight to Kanazawa. This is the start of the road trip!"
      },
      {
        "id": "96735476-b446-423e-9bb3-5c1ba4dc8a5d",
        "label": "Taitung",
        "latitude": 22.755421688207196,
        "longitude": 121.1485379073298,
        "at": "2025-12-24T11:30:00.000Z",
        "note": "Spending Christmas with DQ"
      },
      {
        "id": "eb43a1c1-bd23-44af-95dc-b0a5e7fab99f",
        "label": "Taipei",
        "latitude": 25.03346844531645,
        "longitude": 121.56495420459811,
        "at": "2025-12-23T08:15:00.000Z",
        "note": "Taipei layover for Taitung"
      },
      {
        "id": "0a7321fb-21d3-4b4d-9005-4358fe5b3555",
        "label": "Tokyo",
        "latitude": 35.68906097726562,
        "longitude": 139.71508499653592,
        "at": "2025-12-01T14:30:00.000Z",
        "note": "Working remotely in Tokyo for a month"
      },
      {
        "id": "df073ae0-2e02-4e23-9a3b-a49a72ce31b0",
        "label": "San Francisco",
        "latitude": 37.62193970897527,
        "longitude": -122.38251453291625,
        "at": "2025-11-26T12:00:00.000Z",
        "note": "Friendsgiving"
      },
      {
        "id": "83d22273-651b-4267-887f-9bfbac33a8aa",
        "label": "Ine",
        "latitude": 35.67573145950988,
        "longitude": 135.2868706731373,
        "at": "2026-03-07T04:00:00.000Z",
        "note": "Staying overnight at a quaint fishing village"
      },
      {
        "id": "bf17b376-b072-4af6-9484-bf80345dc59f",
        "label": "Tottori",
        "latitude": 35.41206474296221,
        "longitude": 133.89358911549002,
        "at": "2026-03-08T09:00:00.000Z",
        "note": "Staying at a hot spring hotel with a beautiful garden (Izanro Iwasaki)."
      },
      {
        "id": "fb8591b5-90db-41c7-9144-f7bf74fcfa7c",
        "label": "Shenzhen",
        "latitude": 22.53819,
        "longitude": 114.059852,
        "at": "2026-03-03T04:00:00.000Z",
        "note": "Visiting a mega spa in Shenzhen"
      },
      {
        "id": "79e8143e-9a5e-4c69-94ba-dd0a5305189a",
        "label": "Shirakawa-go",
        "latitude": 36.25788318584295,
        "longitude": 136.9058863602385,
        "at": "2026-03-05T00:30:00.000Z",
        "note": "Sunny day today, made a last minute pivot to visit Shirakawa-go. Almost couldn't get back to Kanazawa!!!"
      }
    ]
  },
  "categories": [
    "personal",
    "film",
    "portrait"
  ],
  "projectOrder": [
    "the-bridge-reconstructed",
    "urban-courts",
    "desolate-sands",
    "locke",
    "ethereal",
    "portraits",
    "figma-2025",
    "figma-2023",
    "figma",
    "yukimi-justin",
    "dustin"
  ],
  "featuredProjectSlugs": [
    "the-bridge-reconstructed",
    "portraits",
    "desolate-sands",
    "urban-courts"
  ]
}
